opticalc.py
opticalc-0.0.1.dist-info/LICENSE
opticalc-0.0.1.dist-info/METADATA
opticalc-0.0.1.dist-info/WHEEL
opticalc-0.0.1.dist-info/top_level.txt
opticalc-0.0.1.dist-info/RECORD
